easy_infra/__init__.py
easy_infra/__main__.py
easy_infra/commands/__init__.py
easy_infra/commands/bootstrap.py
easy_infra/commands/utils.py
easy_infra/commands/utils_aws.py
easy_infra-0.0.0.data/data/examples/easy.yml
easy_infra-0.0.0.data/data/examples/full.yml
easy_infra-0.0.0.data/data/examples/minimal.yml
easy_infra-0.0.0.dist-info/AUTHORS
easy_infra-0.0.0.dist-info/LICENSE
easy_infra-0.0.0.dist-info/METADATA
easy_infra-0.0.0.dist-info/WHEEL
easy_infra-0.0.0.dist-info/entry_points.txt
easy_infra-0.0.0.dist-info/pbr.json
easy_infra-0.0.0.dist-info/top_level.txt
easy_infra-0.0.0.dist-info/RECORD
