Metadata-Version: 2.1
Name: easy-infra
Version: 0.0.0
Summary: UNKNOWN
Home-page: UNKNOWN
Author: Ringier Tech
Author-email: tools@ringier.co.za
License: UNKNOWN
Project-URL: Bug Tracker, https://github.com/RingierIMU/easy-infra/issues
Project-URL: Source Code, https://github.com/RingierIMU/easy-infra
Keywords: setup,laravel,terraform
Platform: UNKNOWN
Classifier: Programming Language :: Python
Classifier: Programming Language :: Python :: 3
Requires-Python: >=3.8
Requires-Dist: boto3
Requires-Dist: click
Requires-Dist: click-default-group
Requires-Dist: click-log
Requires-Dist: pyyaml
Requires-Dist: wheel
Provides-Extra: dev
Requires-Dist: black ; extra == 'dev'
Requires-Dist: flake8 ; extra == 'dev'
Requires-Dist: pylint ; extra == 'dev'
Requires-Dist: pyright ; extra == 'dev'
Requires-Dist: twine ; extra == 'dev'
